fluid_report/__init__.py
fluid_report/exceptions.py
fluid_report/pdf_downloader.py
fluid_report/queries.yaml
fluid_report/reportbot.py
fluid_report/transformers.py
fluid_report/workers.py
fluid_report-1.1.7.dist-info/METADATA
fluid_report-1.1.7.dist-info/WHEEL
fluid_report-1.1.7.dist-info/entry_points.txt
fluid_report-1.1.7.dist-info/top_level.txt
fluid_report-1.1.7.dist-info/RECORD
