Metadata-Version: 2.1
Name: fluid-report
Version: 1.1.7
Summary: UNKNOWN
Home-page: http://pypi.lodgenet.com/simple/fluid_report
Author: A-Team Developers
Author-email: atd@lodgenet.com
License: UNKNOWN
Platform: UNKNOWN
Requires-Dist: fluid-mq (>=3.0.0rc2)
Requires-Dist: splunk-sdk (==1.6.0)
Requires-Dist: iso8601 (==0.1.10)
Requires-Dist: six (==1.10.0)
Requires-Dist: requests-toolbelt (==0.6.0)
